.gitignore
CHANGES.txt
CONTRIBUTORS.txt
README.rst
setup.py
djb/__init__.py
djb.headerproxy.egg-info/PKG-INFO
djb.headerproxy.egg-info/SOURCES.txt
djb.headerproxy.egg-info/dependency_links.txt
djb.headerproxy.egg-info/entry_points.txt
djb.headerproxy.egg-info/namespace_packages.txt
djb.headerproxy.egg-info/not-zip-safe
djb.headerproxy.egg-info/requires.txt
djb.headerproxy.egg-info/top_level.txt
djb/headerproxy/__init__.py
docs/LICENSE.GPL
docs/LICENSE.txt