Metadata-Version: 1.0
Name: djb.headerproxy
Version: 0.1.1
Summary: Paste proxies with the ability to proxy to a location based upon an incoming header
Home-page: http://github.com/davidjb/djb.headerproxy/
Author: David Beitey
Author-email: python@davidjb.com
License: gpl
Keywords: proxy paste headers http
Platform: UNKNOWN
Classifier: Programming Language :: Python
